tests/__init__.py
tests/test_scraper.py
youtube_scraper/__init__.py
youtube_scraper/scraper.py
youtube_scraper-1.0.3.dist-info/LICENSE
youtube_scraper-1.0.3.dist-info/METADATA
youtube_scraper-1.0.3.dist-info/WHEEL
youtube_scraper-1.0.3.dist-info/top_level.txt
youtube_scraper-1.0.3.dist-info/zip-safe
youtube_scraper-1.0.3.dist-info/RECORD
